[
    {
        "_configuration": {
            "genericOrSpecificParsing": true,
            "verbAssociatorUsed": false,
            "verbAssociatorProximityBasedOrSyntacticBased": true,
            "hypernymMutation": true,
            "closedOrMaximalPattern": false,
            "minSupport": 1
        },
        "_activityResults": [
            {
                "_activityName": "answer_the_phone",
                "_pathToWebPages": "C:/Users/Charles/WebstormProjects/webpages_retrieval/oldOutputDataComplete/answer_the_phone",
                "_frequentSequentialPatterns": [
                    {
                        "pattern": [
                            "telephone",
                            "telephone",
                            "telephone",
                            "telephone",
                            "telephone",
                            "telephone",
                            "telephone"
                        ],
                        "patternFrequency": 0.7745664739884393,
                        "inverseActivityFrequency": 1.255272505103306,
                        "pfIaf": 0.9722919981725029
                    },
                    {
                        "pattern": [
                            "junction"
                        ],
                        "patternFrequency": 0.815028901734104,
                        "inverseActivityFrequency": 0.9542425094393249,
                        "pfIaf": 0.7777352244563284
                    },
                    {
                        "pattern": [
                            "way"
                        ],
                        "patternFrequency": 0.7514450867052023,
                        "inverseActivityFrequency": 0.7781512503836436,
                        "pfIaf": 0.5847379338142986
                    }
                ],
                "_numberOfPatterns": 3,
                "_typeOfPattern": "closed",
                "_numberOfPlans": 173,
                "_minSupport": 0.7499999999999998,
                "_minNumberPatterns": 3,
                "_dateBegin": "2021-03-29T05:00:40.596Z",
                "_dateEnd": "2021-03-29T05:00:40.996Z"
            },
            {
                "_activityName": "bake_parmesan_turkey_meatballs",
                "_pathToWebPages": "C:/Users/Charles/WebstormProjects/webpages_retrieval/oldOutputDataComplete/bake_parmesan_turkey_meatballs",
                "_frequentSequentialPatterns": [
                    {
                        "pattern": [
                            "dish",
                            "dish",
                            "dish"
                        ],
                        "patternFrequency": 0.9615384615384616,
                        "inverseActivityFrequency": 1.255272505103306,
                        "pfIaf": 1.2069927933685636
                    },
                    {
                        "pattern": [
                            "dish",
                            "dish",
                            "food"
                        ],
                        "patternFrequency": 0.9423076923076923,
                        "inverseActivityFrequency": 0.9542425094393249,
                        "pfIaf": 0.8991900569716715
                    },
                    {
                        "pattern": [
                            "dish",
                            "food",
                            "dish"
                        ],
                        "patternFrequency": 0.9423076923076923,
                        "inverseActivityFrequency": 1.255272505103306,
                        "pfIaf": 1.1828529375011922
                    },
                    {
                        "pattern": [
                            "food",
                            "dish",
                            "dish"
                        ],
                        "patternFrequency": 0.9423076923076923,
                        "inverseActivityFrequency": 1.255272505103306,
                        "pfIaf": 1.1828529375011922
                    }
                ],
                "_numberOfPatterns": 4,
                "_typeOfPattern": "closed",
                "_numberOfPlans": 104,
                "_minSupport": 0.94,
                "_minNumberPatterns": 3,
                "_dateBegin": "2021-03-29T05:01:18.347Z",
                "_dateEnd": "2021-03-29T05:01:18.710Z"
            },
            {
                "_activityName": "choosing_outfit",
                "_pathToWebPages": "C:/Users/Charles/WebstormProjects/webpages_retrieval/oldOutputDataComplete/choosing_outfit",
                "_frequentSequentialPatterns": [
                    {
                        "pattern": [
                            "thing"
                        ],
                        "patternFrequency": 0.7913669064748201,
                        "inverseActivityFrequency": 0.6532125137753437,
                        "pfIaf": 0.5169307662970346
                    },
                    {
                        "pattern": [
                            "attire"
                        ],
                        "patternFrequency": 0.7841726618705036,
                        "inverseActivityFrequency": 1.255272505103306,
                        "pfIaf": 0.9843503816997148
                    },
                    {
                        "pattern": [
                            "tract"
                        ],
                        "patternFrequency": 0.7769784172661871,
                        "inverseActivityFrequency": 1.255272505103306,
                        "pfIaf": 0.9753196442529285
                    }
                ],
                "_numberOfPatterns": 3,
                "_typeOfPattern": "closed",
                "_numberOfPlans": 139,
                "_minSupport": 0.7699999999999998,
                "_minNumberPatterns": 3,
                "_dateBegin": "2021-03-29T05:02:15.064Z",
                "_dateEnd": "2021-03-29T05:02:15.428Z"
            },
            {
                "_activityName": "clean",
                "_pathToWebPages": "C:/Users/Charles/WebstormProjects/webpages_retrieval/oldOutputDataComplete/clean",
                "_frequentSequentialPatterns": [
                    {
                        "pattern": [
                            "housing"
                        ],
                        "patternFrequency": 0.8345864661654135,
                        "inverseActivityFrequency": 0.7781512503836436,
                        "pfIaf": 0.6494345021998831
                    },
                    {
                        "pattern": [
                            "junction"
                        ],
                        "patternFrequency": 0.8345864661654135,
                        "inverseActivityFrequency": 0.9542425094393249,
                        "pfIaf": 0.7963978838177824
                    },
                    {
                        "pattern": [
                            "way"
                        ],
                        "patternFrequency": 0.8345864661654135,
                        "inverseActivityFrequency": 0.7781512503836436,
                        "pfIaf": 0.6494345021998831
                    },
                    {
                        "pattern": [
                            "structure"
                        ],
                        "patternFrequency": 0.8421052631578947,
                        "inverseActivityFrequency": 1.255272505103306,
                        "pfIaf": 1.0570715832448891
                    }
                ],
                "_numberOfPatterns": 4,
                "_typeOfPattern": "closed",
                "_numberOfPlans": 133,
                "_minSupport": 0.8299999999999998,
                "_minNumberPatterns": 3,
                "_dateBegin": "2021-03-29T05:03:13.413Z",
                "_dateEnd": "2021-03-29T05:03:13.855Z"
            },
            {
                "_activityName": "cook_pasta",
                "_pathToWebPages": "C:/Users/Charles/WebstormProjects/webpages_retrieval/oldOutputDataComplete/cook_pasta",
                "_frequentSequentialPatterns": [
                    {
                        "pattern": [
                            "food",
                            "dish"
                        ],
                        "patternFrequency": 0.8636363636363636,
                        "inverseActivityFrequency": 1.255272505103306,
                        "pfIaf": 1.0840989816801279
                    },
                    {
                        "pattern": [
                            "dish",
                            "dish",
                            "food"
                        ],
                        "patternFrequency": 0.8636363636363636,
                        "inverseActivityFrequency": 0.9542425094393249,
                        "pfIaf": 0.8241185308794169
                    },
                    {
                        "pattern": [
                            "dish",
                            "dish",
                            "dish",
                            "dish",
                            "dish",
                            "dish",
                            "dish",
                            "dish",
                            "dish",
                            "dish",
                            "dish",
                            "dish"
                        ],
                        "patternFrequency": 0.8712121212121212,
                        "inverseActivityFrequency": 1.255272505103306,
                        "pfIaf": 1.0936086218703045
                    }
                ],
                "_numberOfPatterns": 3,
                "_typeOfPattern": "closed",
                "_numberOfPlans": 132,
                "_minSupport": 0.8599999999999999,
                "_minNumberPatterns": 3,
                "_dateBegin": "2021-03-29T05:04:07.780Z",
                "_dateEnd": "2021-03-29T05:04:09.157Z"
            },
            {
                "_activityName": "do_homework",
                "_pathToWebPages": "C:/Users/Charles/WebstormProjects/webpages_retrieval/oldOutputDataComplete/do_homework",
                "_frequentSequentialPatterns": [
                    {
                        "pattern": [
                            "thing"
                        ],
                        "patternFrequency": 0.9024390243902439,
                        "inverseActivityFrequency": 0.6532125137753437,
                        "pfIaf": 0.58948446365092
                    },
                    {
                        "pattern": [
                            "building"
                        ],
                        "patternFrequency": 0.8780487804878049,
                        "inverseActivityFrequency": 1.255272505103306,
                        "pfIaf": 1.1021904922858297
                    },
                    {
                        "pattern": [
                            "work"
                        ],
                        "patternFrequency": 0.8475609756097561,
                        "inverseActivityFrequency": 1.255272505103306,
                        "pfIaf": 1.0639199890814606
                    }
                ],
                "_numberOfPatterns": 3,
                "_typeOfPattern": "closed",
                "_numberOfPlans": 164,
                "_minSupport": 0.8399999999999999,
                "_minNumberPatterns": 3,
                "_dateBegin": "2021-03-29T05:05:10.229Z",
                "_dateEnd": "2021-03-29T05:05:10.470Z"
            },
            {
                "_activityName": "fill_medicine_cabinet",
                "_pathToWebPages": "C:/Users/Charles/WebstormProjects/webpages_retrieval/oldOutputDataComplete/fill_medicine_cabinet",
                "_frequentSequentialPatterns": [
                    {
                        "pattern": [
                            "housing"
                        ],
                        "patternFrequency": 0.8584905660377359,
                        "inverseActivityFrequency": 0.7781512503836436,
                        "pfIaf": 0.6680355074048262
                    },
                    {
                        "pattern": [
                            "furniture"
                        ],
                        "patternFrequency": 0.8773584905660378,
                        "inverseActivityFrequency": 1.255272505103306,
                        "pfIaf": 1.1013239903264855
                    },
                    {
                        "pattern": [
                            "room"
                        ],
                        "patternFrequency": 0.8679245283018868,
                        "inverseActivityFrequency": 1.255272505103306,
                        "pfIaf": 1.0894817968821147
                    }
                ],
                "_numberOfPatterns": 3,
                "_typeOfPattern": "closed",
                "_numberOfPlans": 106,
                "_minSupport": 0.8499999999999999,
                "_minNumberPatterns": 3,
                "_dateBegin": "2021-03-29T05:06:00.283Z",
                "_dateEnd": "2021-03-29T05:06:00.708Z"
            },
            {
                "_activityName": "make_coffee",
                "_pathToWebPages": "C:/Users/Charles/WebstormProjects/webpages_retrieval/oldOutputDataComplete/make_coffee",
                "_frequentSequentialPatterns": [
                    {
                        "pattern": [
                            "beverage",
                            "beverage",
                            "beverage",
                            "beverage",
                            "beverage",
                            "beverage",
                            "beverage",
                            "beverage",
                            "beverage",
                            "beverage",
                            "beverage",
                            "beverage",
                            "beverage",
                            "beverage",
                            "beverage",
                            "beverage"
                        ],
                        "patternFrequency": 0.9322033898305084,
                        "inverseActivityFrequency": 1.255272505103306,
                        "pfIaf": 1.170169284418336
                    },
                    {
                        "pattern": [
                            "dwelling"
                        ],
                        "patternFrequency": 0.9152542372881356,
                        "inverseActivityFrequency": 1.255272505103306,
                        "pfIaf": 1.1488934792470937
                    },
                    {
                        "pattern": [
                            "water"
                        ],
                        "patternFrequency": 0.9152542372881356,
                        "inverseActivityFrequency": 1.255272505103306,
                        "pfIaf": 1.1488934792470937
                    }
                ],
                "_numberOfPatterns": 3,
                "_typeOfPattern": "closed",
                "_numberOfPlans": 118,
                "_minSupport": 0.9099999999999999,
                "_minNumberPatterns": 3,
                "_dateBegin": "2021-03-29T05:06:59.183Z",
                "_dateEnd": "2021-03-29T05:07:01.284Z"
            },
            {
                "_activityName": "make_low_carb_pancakes",
                "_pathToWebPages": "C:/Users/Charles/WebstormProjects/webpages_retrieval/oldOutputDataComplete/make_low_carb_pancakes",
                "_frequentSequentialPatterns": [
                    {
                        "pattern": [
                            "cake",
                            "cake",
                            "cake",
                            "cake",
                            "cake",
                            "cake",
                            "cake"
                        ],
                        "patternFrequency": 0.9459459459459459,
                        "inverseActivityFrequency": 1.255272505103306,
                        "pfIaf": 1.1874199372598842
                    },
                    {
                        "pattern": [
                            "cake",
                            "cake",
                            "cake",
                            "cake",
                            "food"
                        ],
                        "patternFrequency": 0.9459459459459459,
                        "inverseActivityFrequency": 1.255272505103306,
                        "pfIaf": 1.1874199372598842
                    },
                    {
                        "pattern": [
                            "food",
                            "cake",
                            "cake",
                            "cake"
                        ],
                        "patternFrequency": 0.9459459459459459,
                        "inverseActivityFrequency": 1.255272505103306,
                        "pfIaf": 1.1874199372598842
                    },
                    {
                        "pattern": [
                            "food",
                            "food"
                        ],
                        "patternFrequency": 0.9459459459459459,
                        "inverseActivityFrequency": 0.9542425094393249,
                        "pfIaf": 0.9026618332534154
                    }
                ],
                "_numberOfPatterns": 4,
                "_typeOfPattern": "closed",
                "_numberOfPlans": 148,
                "_minSupport": 0.94,
                "_minNumberPatterns": 3,
                "_dateBegin": "2021-03-29T05:08:02.278Z",
                "_dateEnd": "2021-03-29T05:08:03.747Z"
            },
            {
                "_activityName": "make_mashed_potato_casserole",
                "_pathToWebPages": "C:/Users/Charles/WebstormProjects/webpages_retrieval/oldOutputDataComplete/make_mashed_potato_casserole",
                "_frequentSequentialPatterns": [
                    {
                        "pattern": [
                            "dish",
                            "potato",
                            "potato",
                            "potato",
                            "dish"
                        ],
                        "patternFrequency": 0.9403973509933775,
                        "inverseActivityFrequency": 1.255272505103306,
                        "pfIaf": 1.18045493857397
                    },
                    {
                        "pattern": [
                            "potato",
                            "dish",
                            "potato",
                            "potato"
                        ],
                        "patternFrequency": 0.9403973509933775,
                        "inverseActivityFrequency": 1.255272505103306,
                        "pfIaf": 1.18045493857397
                    },
                    {
                        "pattern": [
                            "potato",
                            "potato",
                            "potato",
                            "potato"
                        ],
                        "patternFrequency": 0.9403973509933775,
                        "inverseActivityFrequency": 1.255272505103306,
                        "pfIaf": 1.18045493857397
                    }
                ],
                "_numberOfPatterns": 3,
                "_typeOfPattern": "closed",
                "_numberOfPlans": 151,
                "_minSupport": 0.94,
                "_minNumberPatterns": 3,
                "_dateBegin": "2021-03-29T05:08:50.689Z",
                "_dateEnd": "2021-03-29T05:08:51.976Z"
            },
            {
                "_activityName": "make_stuffed_crust_pizza",
                "_pathToWebPages": "C:/Users/Charles/WebstormProjects/webpages_retrieval/oldOutputDataComplete/make_stuffed_crust_pizza",
                "_frequentSequentialPatterns": [
                    {
                        "pattern": [
                            "layer",
                            "dish"
                        ],
                        "patternFrequency": 0.9415584415584416,
                        "inverseActivityFrequency": 1.255272505103306,
                        "pfIaf": 1.1819124236362297
                    },
                    {
                        "pattern": [
                            "dish",
                            "layer"
                        ],
                        "patternFrequency": 0.935064935064935,
                        "inverseActivityFrequency": 1.255272505103306,
                        "pfIaf": 1.1737613034732213
                    },
                    {
                        "pattern": [
                            "dish",
                            "dish"
                        ],
                        "patternFrequency": 0.935064935064935,
                        "inverseActivityFrequency": 1.255272505103306,
                        "pfIaf": 1.1737613034732213
                    }
                ],
                "_numberOfPatterns": 3,
                "_typeOfPattern": "closed",
                "_numberOfPlans": 154,
                "_minSupport": 0.9299999999999999,
                "_minNumberPatterns": 3,
                "_dateBegin": "2021-03-29T05:09:39.657Z",
                "_dateEnd": "2021-03-29T05:09:40.369Z"
            },
            {
                "_activityName": "make_tea",
                "_pathToWebPages": "C:/Users/Charles/WebstormProjects/webpages_retrieval/oldOutputDataComplete/make_tea",
                "_frequentSequentialPatterns": [
                    {
                        "pattern": [
                            "beverage",
                            "beverage",
                            "beverage",
                            "beverage",
                            "beverage",
                            "beverage",
                            "beverage",
                            "beverage",
                            "beverage",
                            "beverage",
                            "beverage",
                            "beverage",
                            "beverage",
                            "beverage",
                            "beverage"
                        ],
                        "patternFrequency": 0.8712121212121212,
                        "inverseActivityFrequency": 1.255272505103306,
                        "pfIaf": 1.0936086218703045
                    },
                    {
                        "pattern": [
                            "beverage",
                            "beverage",
                            "beverage",
                            "cup",
                            "beverage"
                        ],
                        "patternFrequency": 0.8712121212121212,
                        "inverseActivityFrequency": 1.255272505103306,
                        "pfIaf": 1.0936086218703045
                    },
                    {
                        "pattern": [
                            "beverage",
                            "beverage",
                            "beverage",
                            "water"
                        ],
                        "patternFrequency": 0.8712121212121212,
                        "inverseActivityFrequency": 1.255272505103306,
                        "pfIaf": 1.0936086218703045
                    }
                ],
                "_numberOfPatterns": 3,
                "_typeOfPattern": "closed",
                "_numberOfPlans": 132,
                "_minSupport": 0.8699999999999999,
                "_minNumberPatterns": 3,
                "_dateBegin": "2021-03-29T05:10:44.027Z",
                "_dateEnd": "2021-03-29T05:10:46.460Z"
            },
            {
                "_activityName": "play_video_games",
                "_pathToWebPages": "C:/Users/Charles/WebstormProjects/webpages_retrieval/oldOutputDataComplete/play_video_games",
                "_frequentSequentialPatterns": [
                    {
                        "pattern": [
                            "thing"
                        ],
                        "patternFrequency": 0.859375,
                        "inverseActivityFrequency": 0.6532125137753437,
                        "pfIaf": 0.561354504025686
                    },
                    {
                        "pattern": [
                            "game",
                            "game",
                            "game",
                            "game",
                            "game",
                            "game",
                            "game",
                            "game",
                            "game",
                            "game",
                            "game"
                        ],
                        "patternFrequency": 0.8515625,
                        "inverseActivityFrequency": 1.255272505103306,
                        "pfIaf": 1.068942992627034
                    },
                    {
                        "pattern": [
                            "recording",
                            "game"
                        ],
                        "patternFrequency": 0.8671875,
                        "inverseActivityFrequency": 1.255272505103306,
                        "pfIaf": 1.0885566255192731
                    }
                ],
                "_numberOfPatterns": 3,
                "_typeOfPattern": "closed",
                "_numberOfPlans": 128,
                "_minSupport": 0.8499999999999999,
                "_minNumberPatterns": 3,
                "_dateBegin": "2021-03-29T05:11:54.654Z",
                "_dateEnd": "2021-03-29T05:11:55.863Z"
            },
            {
                "_activityName": "prepare_birthday_card",
                "_pathToWebPages": "C:/Users/Charles/WebstormProjects/webpages_retrieval/oldOutputDataComplete/prepare_birthday_card",
                "_frequentSequentialPatterns": [
                    {
                        "pattern": [
                            "paper",
                            "paper",
                            "paper",
                            "paper",
                            "paper",
                            "paper",
                            "paper",
                            "paper",
                            "paper",
                            "paper",
                            "paper"
                        ],
                        "patternFrequency": 0.7986111111111112,
                        "inverseActivityFrequency": 1.255272505103306,
                        "pfIaf": 1.002474570047779
                    },
                    {
                        "pattern": [
                            "paper",
                            "paper",
                            "paper",
                            "representation"
                        ],
                        "patternFrequency": 0.7708333333333334,
                        "inverseActivityFrequency": 1.255272505103306,
                        "pfIaf": 0.9676058893504651
                    },
                    {
                        "pattern": [
                            "representation",
                            "paper",
                            "paper"
                        ],
                        "patternFrequency": 0.7708333333333334,
                        "inverseActivityFrequency": 1.255272505103306,
                        "pfIaf": 0.9676058893504651
                    }
                ],
                "_numberOfPatterns": 3,
                "_typeOfPattern": "closed",
                "_numberOfPlans": 144,
                "_minSupport": 0.7699999999999998,
                "_minNumberPatterns": 3,
                "_dateBegin": "2021-03-29T05:12:57.554Z",
                "_dateEnd": "2021-03-29T05:12:58.533Z"
            },
            {
                "_activityName": "prepare_soup",
                "_pathToWebPages": "C:/Users/Charles/WebstormProjects/webpages_retrieval/oldOutputDataComplete/prepare_soup",
                "_frequentSequentialPatterns": [
                    {
                        "pattern": [
                            "food",
                            "food"
                        ],
                        "patternFrequency": 0.9150326797385621,
                        "inverseActivityFrequency": 0.9542425094393249,
                        "pfIaf": 0.8731630805327155
                    },
                    {
                        "pattern": [
                            "food",
                            "dish",
                            "dish",
                            "dish",
                            "dish"
                        ],
                        "patternFrequency": 0.9150326797385621,
                        "inverseActivityFrequency": 1.255272505103306,
                        "pfIaf": 1.148615364146816
                    },
                    {
                        "pattern": [
                            "dish",
                            "dish",
                            "dish",
                            "dish",
                            "dish",
                            "dish",
                            "dish"
                        ],
                        "patternFrequency": 0.9150326797385621,
                        "inverseActivityFrequency": 1.255272505103306,
                        "pfIaf": 1.148615364146816
                    }
                ],
                "_numberOfPatterns": 3,
                "_typeOfPattern": "closed",
                "_numberOfPlans": 153,
                "_minSupport": 0.9099999999999999,
                "_minNumberPatterns": 3,
                "_dateBegin": "2021-03-29T05:13:58.802Z",
                "_dateEnd": "2021-03-29T05:14:00.084Z"
            },
            {
                "_activityName": "vacuum",
                "_pathToWebPages": "C:/Users/Charles/WebstormProjects/webpages_retrieval/oldOutputDataComplete/vacuum",
                "_frequentSequentialPatterns": [
                    {
                        "pattern": [
                            "housing"
                        ],
                        "patternFrequency": 0.8287671232876712,
                        "inverseActivityFrequency": 0.7781512503836436,
                        "pfIaf": 0.6449061732631567
                    },
                    {
                        "pattern": [
                            "vacuum",
                            "vacuum",
                            "vacuum",
                            "vacuum",
                            "vacuum",
                            "vacuum",
                            "vacuum",
                            "vacuum",
                            "vacuum"
                        ],
                        "patternFrequency": 0.815068493150685,
                        "inverseActivityFrequency": 1.255272505103306,
                        "pfIaf": 1.0231330692280372
                    },
                    {
                        "pattern": [
                            "thing"
                        ],
                        "patternFrequency": 0.815068493150685,
                        "inverseActivityFrequency": 0.6532125137753437,
                        "pfIaf": 0.5324129393100404
                    }
                ],
                "_numberOfPatterns": 3,
                "_typeOfPattern": "closed",
                "_numberOfPlans": 146,
                "_minSupport": 0.8099999999999998,
                "_minNumberPatterns": 3,
                "_dateBegin": "2021-03-29T05:15:11.649Z",
                "_dateEnd": "2021-03-29T05:15:12.554Z"
            },
            {
                "_activityName": "watch_tv",
                "_pathToWebPages": "C:/Users/Charles/WebstormProjects/webpages_retrieval/oldOutputDataComplete/watch_tv",
                "_frequentSequentialPatterns": [
                    {
                        "pattern": [
                            "way"
                        ],
                        "patternFrequency": 0.7602739726027398,
                        "inverseActivityFrequency": 0.7781512503836436,
                        "pfIaf": 0.591608142414962
                    },
                    {
                        "pattern": [
                            "receiver",
                            "receiver",
                            "receiver",
                            "receiver",
                            "receiver",
                            "receiver",
                            "receiver",
                            "receiver",
                            "receiver"
                        ],
                        "patternFrequency": 0.7671232876712328,
                        "inverseActivityFrequency": 1.255272505103306,
                        "pfIaf": 0.9629487710381525
                    },
                    {
                        "pattern": [
                            "device"
                        ],
                        "patternFrequency": 0.7876712328767124,
                        "inverseActivityFrequency": 1.255272505103306,
                        "pfIaf": 0.9887420416909602
                    }
                ],
                "_numberOfPatterns": 3,
                "_typeOfPattern": "closed",
                "_numberOfPlans": 146,
                "_minSupport": 0.7599999999999998,
                "_minNumberPatterns": 3,
                "_dateBegin": "2021-03-29T05:16:17.217Z",
                "_dateEnd": "2021-03-29T05:16:18.167Z"
            },
            {
                "_activityName": "water_plants",
                "_pathToWebPages": "C:/Users/Charles/WebstormProjects/webpages_retrieval/oldOutputDataComplete/water_plants",
                "_frequentSequentialPatterns": [
                    {
                        "pattern": [
                            "plant",
                            "plant",
                            "plant",
                            "plant"
                        ],
                        "patternFrequency": 0.9407894736842105,
                        "inverseActivityFrequency": 1.255272505103306,
                        "pfIaf": 1.1809471594063996
                    },
                    {
                        "pattern": [
                            "plant",
                            "plant",
                            "plant",
                            "water"
                        ],
                        "patternFrequency": 0.9407894736842105,
                        "inverseActivityFrequency": 1.255272505103306,
                        "pfIaf": 1.1809471594063996
                    },
                    {
                        "pattern": [
                            "plant",
                            "plant",
                            "water",
                            "plant"
                        ],
                        "patternFrequency": 0.9473684210526315,
                        "inverseActivityFrequency": 1.255272505103306,
                        "pfIaf": 1.1892055311505003
                    },
                    {
                        "pattern": [
                            "plant",
                            "water",
                            "plant",
                            "plant"
                        ],
                        "patternFrequency": 0.9407894736842105,
                        "inverseActivityFrequency": 1.255272505103306,
                        "pfIaf": 1.1809471594063996
                    },
                    {
                        "pattern": [
                            "water",
                            "plant",
                            "plant",
                            "plant"
                        ],
                        "patternFrequency": 0.9407894736842105,
                        "inverseActivityFrequency": 1.255272505103306,
                        "pfIaf": 1.1809471594063996
                    },
                    {
                        "pattern": [
                            "water",
                            "water"
                        ],
                        "patternFrequency": 0.9407894736842105,
                        "inverseActivityFrequency": 1.255272505103306,
                        "pfIaf": 1.1809471594063996
                    }
                ],
                "_numberOfPatterns": 6,
                "_typeOfPattern": "closed",
                "_numberOfPlans": 152,
                "_minSupport": 0.94,
                "_minNumberPatterns": 3,
                "_dateBegin": "2021-03-29T05:17:27.373Z",
                "_dateEnd": "2021-03-29T05:17:29.294Z"
            }
        ],
        "_dateBegin": "2021-03-29T04:59:37.415Z",
        "_dateEnd": "2021-03-29T05:17:29.296Z"
    }
]